{
    "id": 108108961,
    "name": "GDCP Filler Brrrrr",
    "author": "SadCraft0o",
    "creators": [],
    "verifier": "SadCraft0o",
    "verification": "https://youtu.be/AmllHUPVEas",
    "percentToQualify": "100",
    "password": "free",
    "records": [
        {
            "user": "Voiddle",
            "percent": 100,
            "hz": "8.458"
        },
         {
            "user": "Gp0",
            "percent": 100,
            "hz": "8.941"
        },
        {
            "user": "Maxa",
            "percent": 100,
            "hz": "9.704"
        },
        {
            "user": "Ragequit",
            "percent": 100,
            "hz": "16.029"
        },
        {
            "user": "Turbometric",
            "percent": 100,
            "hz": "18.425"
        },  
        {
            "user": "EndGrain",
            "percent": 100,
            "hz": "18.620"
        },
        {
            "user": "cheems",
            "percent": 100,
            "hz": "19.395"
        },
        {
            "user": "Miksutic",
            "hz": "19.854",
            "percent": 100
        },
        {
            "user": "Mylam999",
            "percent": 100,
            "hz": "20.162",
            "mobile": true
        },
        {
            "user": "SH4IN3",
            "percent": 100,
            "hz": "24.687"
        },
        {
            "user": "Flip",
            "percent": 100,
            "hz": "24.870"
        },
        {
            "user": "Allu",
            "percent": 100,
            "hz": "25.295"
        },
        {
            "user": "Mylam999's sister",
            "hz": "27.194",
            "percent": 100
        },
        {
            "user": "Leoalas",
            "hz": "27.883",
            "percent": 100
        },
        {
            "user": "SoulsShards",
            "percent": 100,
            "hz": "28.020",
            "mobile": true
        },
        {
            "user": "EABH",
            "hz": "32.450",
            "percent": 100
        }
    ]
}
