{
    "id": 115688915,
    "name": "jazzy",
    "author": "William",
    "creators": [],
    "verifier": "William",
    "verification": "https://www.youtube.com/watch?v=zuDKiV0FmT8&ab_channel=GameFusion",
    "percentToQualify": "100",
    "password": "free",
    "records": [
        {
            "user": "Voiddle",
            "percent": 100,
            "hz": "8.416"
        },
        {
            "user": "Blurmbog",
            "percent": 100,
            "hz": "9.079"
        },
        {
            "user": "Ragequit",
            "percent": 100,
            "hz": "9.595"
        },
        {
            "user": "Turbometric",
            "percent": 100,
            "hz": "10.741"
        },
        {
            "user": "icarocarli",
            "percent": 100,
            "hz": "12.854"
        },
        {
            "user": "Coffee shlup",
            "percent": 100,
            "hz": "13.062"
        },
        {
            "user": "TheYapKing",
            "percent": 100,
            "hz": "13.266"
        },
        {
            "user": "Maxa",
            "percent": 100,
            "hz": "13.412"
        },
        {
            "user": "Leoalas",
            "hz": "13.950",
            "percent": 100
        },
        {
            "user": "Mylam999",
            "percent": 100,
            "hz": "15.250",
            "mobile": true
        },
        {
            "user": "BLUJAYOO",
            "percent": 100,
            "hz": "15.287"
        },
        {
            "user": "Tsa",
            "percent": 100,
            "hz": "18.233"
        },
        {
            "user": "DeceptiveGD",
            "percent": 100,
            "hz": "21.666"
        }
    ]
}
